{
    "version": "v2",
    "connection_uri": {
        "variable": "JDBC_URL"
    },
    "tables": [
        {
            "name": "docs_bot.doc_chunk",
            "description": null,
            "category": "TABLE",
            "columns": [
                {
                    "name": "id",
                    "nullable": false,
                    "auto_increment": false,
                    "is_primarykey": true,
                    "data": {
                        "database_type": "uuid"
                    }
                },
                {
                    "name": "created_at",
                    "nullable": false,
                    "auto_increment": false,
                    "is_primarykey": false,
                    "data": {
                        "database_type": "timestamp_with_time_zone"
                    }
                },
                {
                    "name": "updated_at",
                    "nullable": false,
                    "auto_increment": false,
                    "is_primarykey": false,
                    "data": {
                        "database_type": "timestamp_with_time_zone"
                    }
                },
                {
                    "name": "doc_content_id_fk",
                    "nullable": false,
                    "auto_increment": false,
                    "is_primarykey": false,
                    "data": {
                        "database_type": "uuid"
                    }
                },
                {
                    "name": "chunk_content",
                    "nullable": false,
                    "auto_increment": false,
                    "is_primarykey": false,
                    "data": {
                        "database_type": "text"
                    }
                },
                {
                    "name": "page_description",
                    "nullable": true,
                    "auto_increment": false,
                    "is_primarykey": false,
                    "data": {
                        "database_type": "text"
                    }
                },
                {
                    "name": "page_keywords",
                    "nullable": true,
                    "auto_increment": false,
                    "is_primarykey": false,
                    "data": {
                        "database_type": "array",
                        "metadata": {
                            "type": "array",
                            "array_types": {
                                "database_type": "text"
                            }
                        }
                    }
                },
                {
                    "name": "page_title",
                    "nullable": true,
                    "auto_increment": false,
                    "is_primarykey": false,
                    "data": {
                        "database_type": "text"
                    }
                },
                {
                    "name": "page_url",
                    "nullable": false,
                    "auto_increment": false,
                    "is_primarykey": false,
                    "data": {
                        "database_type": "text"
                    }
                },
                {
                    "name": "chunk_line_start",
                    "nullable": false,
                    "auto_increment": false,
                    "is_primarykey": false,
                    "data": {
                        "database_type": "integer",
                        "metadata": {
                            "type": "numeric",
                            "precision": 32,
                            "scale": 0
                        }
                    }
                },
                {
                    "name": "chunk_line_end",
                    "nullable": true,
                    "auto_increment": false,
                    "is_primarykey": false,
                    "data": {
                        "database_type": "integer",
                        "metadata": {
                            "type": "numeric",
                            "precision": 32,
                            "scale": 0
                        }
                    }
                },
                {
                    "name": "version",
                    "description": "Version of Hasura that this chunk belongs to. \"2\", \"3\" or \"promptql\".",
                    "nullable": true,
                    "auto_increment": false,
                    "is_primarykey": false,
                    "data": {
                        "database_type": "text"
                    }
                },
                {
                    "name": "embedding",
                    "nullable": true,
                    "auto_increment": false,
                    "is_primarykey": false,
                    "data": {
                        "database_type": "vector(1536)"
                    }
                }
            ],
            "primary_keys": [
                "id"
            ],
            "foreign_keys": {}
        },
        {
            "name": "docs_bot.doc_content",
            "description": null,
            "category": "TABLE",
            "columns": [
                {
                    "name": "id",
                    "nullable": false,
                    "auto_increment": false,
                    "is_primarykey": true,
                    "data": {
                        "database_type": "uuid"
                    }
                },
                {
                    "name": "created_at",
                    "nullable": false,
                    "auto_increment": false,
                    "is_primarykey": false,
                    "data": {
                        "database_type": "timestamp_with_time_zone"
                    }
                },
                {
                    "name": "updated_at",
                    "nullable": false,
                    "auto_increment": false,
                    "is_primarykey": false,
                    "data": {
                        "database_type": "timestamp_with_time_zone"
                    }
                },
                {
                    "name": "content",
                    "nullable": true,
                    "auto_increment": false,
                    "is_primarykey": false,
                    "data": {
                        "database_type": "text"
                    }
                },
                {
                    "name": "is_checked",
                    "nullable": false,
                    "auto_increment": false,
                    "is_primarykey": false,
                    "data": {
                        "database_type": "boolean"
                    }
                },
                {
                    "name": "version",
                    "description": "Version of Hasura that this documentation page belongs to. \"2\", \"3\" or \"promptql\".",
                    "nullable": false,
                    "auto_increment": false,
                    "is_primarykey": false,
                    "data": {
                        "database_type": "text"
                    }
                },
                {
                    "name": "page_url",
                    "nullable": true,
                    "auto_increment": false,
                    "is_primarykey": false,
                    "data": {
                        "database_type": "text"
                    }
                },
                {
                    "name": "title",
                    "nullable": true,
                    "auto_increment": false,
                    "is_primarykey": false,
                    "data": {
                        "database_type": "text"
                    }
                },
                {
                    "name": "description",
                    "nullable": true,
                    "auto_increment": false,
                    "is_primarykey": false,
                    "data": {
                        "database_type": "text"
                    }
                },
                {
                    "name": "keywords",
                    "nullable": true,
                    "auto_increment": false,
                    "is_primarykey": false,
                    "data": {
                        "database_type": "array",
                        "metadata": {
                            "type": "array",
                            "array_types": {
                                "database_type": "text"
                            }
                        }
                    }
                }
            ],
            "primary_keys": [
                "id"
            ],
            "foreign_keys": {}
        },
        {
            "name": "docs_bot.message",
            "description": null,
            "category": "TABLE",
            "columns": [
                {
                    "name": "id",
                    "nullable": false,
                    "auto_increment": false,
                    "is_primarykey": true,
                    "data": {
                        "database_type": "uuid"
                    }
                },
                {
                    "name": "created_at",
                    "nullable": false,
                    "auto_increment": false,
                    "is_primarykey": false,
                    "data": {
                        "database_type": "timestamp_with_time_zone"
                    }
                },
                {
                    "name": "updated_at",
                    "nullable": false,
                    "auto_increment": false,
                    "is_primarykey": false,
                    "data": {
                        "database_type": "timestamp_with_time_zone"
                    }
                },
                {
                    "name": "docs_user_id",
                    "nullable": true,
                    "auto_increment": false,
                    "is_primarykey": false,
                    "data": {
                        "database_type": "text"
                    }
                },
                {
                    "name": "user_message",
                    "nullable": false,
                    "auto_increment": false,
                    "is_primarykey": false,
                    "data": {
                        "database_type": "text"
                    }
                },
                {
                    "name": "bot_response",
                    "nullable": false,
                    "auto_increment": false,
                    "is_primarykey": false,
                    "data": {
                        "database_type": "text"
                    }
                },
                {
                    "name": "version",
                    "description": "Version of Hasura that this message interaction relates to. \"2\", \"3\" or \"promptql\".",
                    "nullable": false,
                    "auto_increment": false,
                    "is_primarykey": false,
                    "data": {
                        "database_type": "text"
                    }
                },
                {
                    "name": "client_message_thread_id",
                    "nullable": false,
                    "auto_increment": false,
                    "is_primarykey": false,
                    "data": {
                        "database_type": "uuid"
                    }
                },
                {
                    "name": "user_good_quality_bool",
                    "nullable": true,
                    "auto_increment": false,
                    "is_primarykey": false,
                    "data": {
                        "database_type": "boolean"
                    }
                },
                {
                    "name": "user_quality_feedback",
                    "nullable": true,
                    "auto_increment": false,
                    "is_primarykey": false,
                    "data": {
                        "database_type": "text"
                    }
                }
            ],
            "primary_keys": [
                "id"
            ],
            "foreign_keys": {}
        },
        {
            "name": "docs_bot.message_thread",
            "description": null,
            "category": "TABLE",
            "columns": [
                {
                    "name": "id",
                    "nullable": false,
                    "auto_increment": false,
                    "is_primarykey": true,
                    "data": {
                        "database_type": "uuid"
                    }
                },
                {
                    "name": "created_at",
                    "nullable": false,
                    "auto_increment": false,
                    "is_primarykey": false,
                    "data": {
                        "database_type": "timestamp_with_time_zone"
                    }
                },
                {
                    "name": "updated_at",
                    "nullable": false,
                    "auto_increment": false,
                    "is_primarykey": false,
                    "data": {
                        "database_type": "timestamp_with_time_zone"
                    }
                },
                {
                    "name": "client_message_thread_id",
                    "nullable": false,
                    "auto_increment": false,
                    "is_primarykey": false,
                    "data": {
                        "database_type": "uuid"
                    }
                },
                {
                    "name": "slack_thread",
                    "nullable": true,
                    "auto_increment": false,
                    "is_primarykey": false,
                    "data": {
                        "database_type": "text"
                    }
                }
            ],
            "primary_keys": [
                "id"
            ],
            "foreign_keys": {}
        },
        {
            "name": "docs_feedback.doc_feedback",
            "description": "Collection of user feedback from the docs feedback component",
            "category": "TABLE",
            "columns": [
                {
                    "name": "id",
                    "nullable": false,
                    "auto_increment": false,
                    "is_primarykey": true,
                    "data": {
                        "database_type": "uuid"
                    }
                },
                {
                    "name": "created_at",
                    "nullable": false,
                    "auto_increment": false,
                    "is_primarykey": false,
                    "data": {
                        "database_type": "timestamp_with_time_zone"
                    }
                },
                {
                    "name": "updated_at",
                    "nullable": false,
                    "auto_increment": false,
                    "is_primarykey": false,
                    "data": {
                        "database_type": "timestamp_with_time_zone"
                    }
                },
                {
                    "name": "page_title",
                    "nullable": false,
                    "auto_increment": false,
                    "is_primarykey": false,
                    "data": {
                        "database_type": "text"
                    }
                },
                {
                    "name": "page_url",
                    "nullable": false,
                    "auto_increment": false,
                    "is_primarykey": false,
                    "data": {
                        "database_type": "text"
                    }
                },
                {
                    "name": "score",
                    "nullable": false,
                    "auto_increment": false,
                    "is_primarykey": false,
                    "data": {
                        "database_type": "integer",
                        "metadata": {
                            "type": "numeric",
                            "precision": 32,
                            "scale": 0
                        }
                    }
                },
                {
                    "name": "user_feedback",
                    "nullable": false,
                    "auto_increment": false,
                    "is_primarykey": false,
                    "data": {
                        "database_type": "text"
                    }
                },
                {
                    "name": "version",
                    "description": "Version of Hasura that this feedback relates to. \"2\", \"3\" or \"promptql\".",
                    "nullable": false,
                    "auto_increment": false,
                    "is_primarykey": false,
                    "data": {
                        "database_type": "text"
                    }
                },
                {
                    "name": "docs_user_id",
                    "nullable": true,
                    "auto_increment": false,
                    "is_primarykey": false,
                    "data": {
                        "database_type": "text"
                    }
                }
            ],
            "primary_keys": [
                "id"
            ],
            "foreign_keys": {}
        },
        {
            "name": "public.connectors",
            "description": "Stores metadata about DDN Native Data Connectors including associated GitHub repository, unique connector identifier, and designated responsible individual (DRI) which is a relation to the username_mapping table",
            "category": "TABLE",
            "columns": [
                {
                    "name": "id",
                    "description": "Primary key UUID identifying this connector record",
                    "nullable": false,
                    "auto_increment": false,
                    "is_primarykey": true,
                    "data": {
                        "database_type": "uuid"
                    }
                },
                {
                    "name": "connector_name",
                    "description": "Human-readable name of the DDN Native Data Connector",
                    "nullable": false,
                    "auto_increment": false,
                    "is_primarykey": false,
                    "data": {
                        "database_type": "text"
                    }
                },
                {
                    "name": "github_repo",
                    "description": "GitHub repository URL or identifier for the connector (unique)",
                    "nullable": false,
                    "auto_increment": false,
                    "is_primarykey": false,
                    "data": {
                        "database_type": "text"
                    }
                },
                {
                    "name": "connector_id",
                    "description": "Unique identifier string for the connector within the DDN ecosystem",
                    "nullable": false,
                    "auto_increment": false,
                    "is_primarykey": false,
                    "data": {
                        "database_type": "text"
                    }
                },
                {
                    "name": "dri_id",
                    "description": "Foreign key to username_mapping(id) identifying the Designated Responsible Individual for this connector",
                    "nullable": false,
                    "auto_increment": false,
                    "is_primarykey": false,
                    "data": {
                        "database_type": "uuid"
                    }
                }
            ],
            "primary_keys": [
                "id"
            ],
            "foreign_keys": {}
        },
        {
            "name": "public.username_mapping",
            "description": "Maps user identity information including names and various platform handles",
            "category": "TABLE",
            "columns": [
                {
                    "name": "id",
                    "description": "Primary key UUID identifying this user mapping record",
                    "nullable": false,
                    "auto_increment": false,
                    "is_primarykey": true,
                    "data": {
                        "database_type": "uuid"
                    }
                },
                {
                    "name": "name",
                    "description": "Full name or display name of the user",
                    "nullable": true,
                    "auto_increment": false,
                    "is_primarykey": false,
                    "data": {
                        "database_type": "text"
                    }
                },
                {
                    "name": "github_username",
                    "description": "GitHub username for the user (unique)",
                    "nullable": true,
                    "auto_increment": false,
                    "is_primarykey": false,
                    "data": {
                        "database_type": "text"
                    }
                },
                {
                    "name": "slack_username",
                    "description": "Slack username for the user (unique, required)",
                    "nullable": false,
                    "auto_increment": false,
                    "is_primarykey": false,
                    "data": {
                        "database_type": "text"
                    }
                },
                {
                    "name": "linear_username",
                    "description": "Linear username for the user (unique)",
                    "nullable": true,
                    "auto_increment": false,
                    "is_primarykey": false,
                    "data": {
                        "database_type": "text"
                    }
                },
                {
                    "name": "email",
                    "description": "Email address of the user (unique)",
                    "nullable": true,
                    "auto_increment": false,
                    "is_primarykey": false,
                    "data": {
                        "database_type": "text"
                    }
                },
                {
                    "name": "timezone",
                    "description": "IANA timezone identifier for the user, e.g., America/Los_Angeles",
                    "nullable": true,
                    "auto_increment": false,
                    "is_primarykey": false,
                    "data": {
                        "database_type": "text"
                    }
                },
                {
                    "name": "timezone_label",
                    "description": "Human-readable label for the users timezone",
                    "nullable": true,
                    "auto_increment": false,
                    "is_primarykey": false,
                    "data": {
                        "database_type": "text"
                    }
                },
                {
                    "name": "timezone_offset",
                    "description": "UTC offset in minutes for the users timezone",
                    "nullable": true,
                    "auto_increment": false,
                    "is_primarykey": false,
                    "data": {
                        "database_type": "integer",
                        "metadata": {
                            "type": "numeric",
                            "precision": 32,
                            "scale": 0
                        }
                    }
                },
                {
                    "name": "github_user_id",
                    "description": "Unique GitHub user ID for the user",
                    "nullable": true,
                    "auto_increment": false,
                    "is_primarykey": false,
                    "data": {
                        "database_type": "text"
                    }
                },
                {
                    "name": "slack_user_id",
                    "description": "Unique Slack user ID for the user",
                    "nullable": true,
                    "auto_increment": false,
                    "is_primarykey": false,
                    "data": {
                        "database_type": "text"
                    }
                },
                {
                    "name": "linear_user_id",
                    "description": "Unique Linear user ID for the user",
                    "nullable": true,
                    "auto_increment": false,
                    "is_primarykey": false,
                    "data": {
                        "database_type": "text"
                    }
                }
            ],
            "primary_keys": [
                "id"
            ],
            "foreign_keys": {}
        }
    ]
}